Metadata-Version: 1.0
Name: arithmetic-pidouki
Version: 0.1
Summary: The funniest joke in the world
Home-page: http://github.com/arithmetic
Author: Flying Circus
Author-email: 123@example.com
License: MIT
Platform: UNKNOWN
